sqlite_integrated/__init__.py
sqlite_integrated-0.0.4.dist-info/LICENSE
sqlite_integrated-0.0.4.dist-info/METADATA
sqlite_integrated-0.0.4.dist-info/WHEEL
sqlite_integrated-0.0.4.dist-info/top_level.txt
sqlite_integrated-0.0.4.dist-info/RECORD
