Metadata-Version: 2.1
Name: sqlite-integrated
Version: 0.0.4
Summary: Easily manipulate sqlite3 databases with simple syntax
Home-page: https://github.com/BalderHolst/sqlite-integrated
Author: Balder Holst
Author-email: balderwh@gmail.com
License: MIT
Platform: UNKNOWN
Classifier: Operating System :: OS Independent
Classifier: Programming Language :: Python :: 3.7
Classifier: Programming Language :: Python :: 3.8
Classifier: Programming Language :: Python :: 3.9
Classifier: Programming Language :: Python :: 3.10
Classifier: Topic :: Database
Requires-Python: >=3.7
License-File: LICENSE
Requires-Dist: pandas (>=1.3.5)
Provides-Extra: dev
Requires-Dist: pytest ; extra == 'dev'
